catchments/__init__.py
catchments/here.py
catchments/parsers.py
catchments/skobbler.py
catchments/utils.py
catchments-1.1.1.data/scripts/catchments-here.py
catchments-1.1.1.data/scripts/catchments-skobbler.py
catchments-1.1.1.dist-info/DESCRIPTION.rst
catchments-1.1.1.dist-info/METADATA
catchments-1.1.1.dist-info/RECORD
catchments-1.1.1.dist-info/WHEEL
catchments-1.1.1.dist-info/metadata.json
catchments-1.1.1.dist-info/top_level.txt
