Metadata-Version: 2.0
Name: catchments
Version: 1.1.1
Summary: Python wrapper for multiple APIs, that provide catchments-areas
Home-page: http://github.com/Luqqk/catchments
Author: Łukasz Mikołajczak (Luqqk)
Author-email: mikolajczak.luq@gmail.com
License: MIT
Keywords: gis api catchments
Platform: UNKNOWN
Classifier: Development Status :: 5 - Production/Stable
Classifier: License :: OSI Approved :: MIT License
Classifier: Programming Language :: Python :: 3 :: Only
Classifier: Topic :: Scientific/Engineering :: GIS
Requires-Dist: requests
